ibd_dendrogram/__init__.py
ibd_dendrogram/make_distance_matrix.py
ibd_dendrogram-0.12.4.dist-info/METADATA
ibd_dendrogram-0.12.4.dist-info/WHEEL
ibd_dendrogram-0.12.4.dist-info/RECORD
